<?xml version="1.0" encoding="UTF-8" standalone="yes"?>

<channels>

<channel>
<name>VICENTE FERNANDEZ</name>
<thumbnail></thumbnail>
<fanart></fanart>
<items>

<item>
<title>Cuando Manda el Corazon</title>        
<urlsolve>https://www.youtube.com/watch?v=QJSs5_rE0Cs</urlsolve>
<thumbnail></thumbnail>
<fanart></fanart>
</item>

<item>
<title>Ya lo se que tú te vas</title>        
<urlsolve>https://www.youtube.com/watch?v=uWElmgTfdZw</urlsolve>
<thumbnail></thumbnail>
<fanart></fanart>
</item>

<item>
<title>Le Pese A Quien Le Pese</title>        
<urlsolve>https://www.youtube.com/watch?v=Bjsw66Qvk0k</urlsolve>
<thumbnail></thumbnail>
<fanart></fanart>
</item>

<item>
<title>Maldita sea</title>        
<urlsolve>https://www.youtube.com/watch?v=s7K3KGPYq2U</urlsolve>
<thumbnail></thumbnail>
<fanart></fanart>
</item>

<item>
<title>Mi Vejez</title>        
<urlsolve>https://www.youtube.com/watch?v=fULKnO6B72M</urlsolve>
<thumbnail></thumbnail>
<fanart></fanart>
</item>

<item>
<title>Estos Celos</title>        
<urlsolve>https://www.youtube.com/watch?v=xEiDC49Vhq8</urlsolve>
<thumbnail></thumbnail>
<fanart></fanart>
</item>